README.rst
setup.py
corporate_wechat/__init__.py
corporate_wechat/config.py
corporate_wechat/crop_wechat.py
corporate_wechat/error_code.py
corporate_wechat.egg-info/PKG-INFO
corporate_wechat.egg-info/SOURCES.txt
corporate_wechat.egg-info/dependency_links.txt
corporate_wechat.egg-info/top_level.txt
corporate_wechat.egg-info/zip-safe