Metadata-Version: 1.1
Name: corporate-wechat
Version: 1.0.1
Summary: a python liberaries  for cropwechat tutorial.
Home-page: http://www.rocyuan.com/
Author: rocyuan
Author-email: admin@rocyuan.com
License: MIT
Keywords: python wechat cropwechat api
Platform: UNKNOWN
Classifier: License :: OSI Approved :: MIT License
Classifier: Programming Language :: Python
Classifier: Intended Audience :: Developers
Classifier: Operating System :: OS Independent
